odoo/addons/base_user_role_profile/README.rst
odoo/addons/base_user_role_profile/__init__.py
odoo/addons/base_user_role_profile/__manifest__.py
odoo/addons/base_user_role_profile/data/data.xml
odoo/addons/base_user_role_profile/i18n/base_user_role_profile.pot
odoo/addons/base_user_role_profile/i18n/de.po
odoo/addons/base_user_role_profile/i18n/es.po
odoo/addons/base_user_role_profile/models/__init__.py
odoo/addons/base_user_role_profile/models/ir_http.py
odoo/addons/base_user_role_profile/models/profile.py
odoo/addons/base_user_role_profile/models/role.py
odoo/addons/base_user_role_profile/models/user.py
odoo/addons/base_user_role_profile/readme/CONFIGURE.rst
odoo/addons/base_user_role_profile/readme/CONTRIBUTORS.rst
odoo/addons/base_user_role_profile/readme/DESCRIPTION.rst
odoo/addons/base_user_role_profile/readme/USAGE.rst
odoo/addons/base_user_role_profile/security/ir.model.access.csv
odoo/addons/base_user_role_profile/static/description/icon.png
odoo/addons/base_user_role_profile/static/description/index.html
odoo/addons/base_user_role_profile/static/src/js/switch_profile_menu.js
odoo/addons/base_user_role_profile/static/src/xml/templates.xml
odoo/addons/base_user_role_profile/tests/__init__.py
odoo/addons/base_user_role_profile/tests/test_user_role.py
odoo/addons/base_user_role_profile/views/assets.xml
odoo/addons/base_user_role_profile/views/profile.xml
odoo/addons/base_user_role_profile/views/role.xml
odoo/addons/base_user_role_profile/views/user.xml
odoo12_addon_base_user_role_profile-12.0.1.0.0.99.dev8.dist-info/METADATA
odoo12_addon_base_user_role_profile-12.0.1.0.0.99.dev8.dist-info/WHEEL
odoo12_addon_base_user_role_profile-12.0.1.0.0.99.dev8.dist-info/top_level.txt
odoo12_addon_base_user_role_profile-12.0.1.0.0.99.dev8.dist-info/RECORD
